vlcpssh/__init__.py
vlcpssh/channel.py
vlcpssh/sshclient.py
vlcpssh-0.1.5.dist-info/DESCRIPTION.rst
vlcpssh-0.1.5.dist-info/METADATA
vlcpssh-0.1.5.dist-info/RECORD
vlcpssh-0.1.5.dist-info/WHEEL
vlcpssh-0.1.5.dist-info/metadata.json
vlcpssh-0.1.5.dist-info/pbr.json
vlcpssh-0.1.5.dist-info/top_level.txt
