Metadata-Version: 1.0
Name: vlcpssh
Version: 0.1.5
Summary: Integrate paramiko into ssh
Home-page: http://github.com/hubo1016/vlcp-ssh
Author: Hu Bo
Author-email: hubo1016@126.com
License: http://www.apache.org/licenses/LICENSE-2.0
Keywords: VLCP,paramiko
Platform: UNKNOWN
